selenium_account/__init__.py
selenium_account/selenium_account.py
selenium_account-0.2.3.dist-info/LICENSE
selenium_account-0.2.3.dist-info/METADATA
selenium_account-0.2.3.dist-info/WHEEL
selenium_account-0.2.3.dist-info/top_level.txt
selenium_account-0.2.3.dist-info/RECORD
