Metadata-Version: 2.1
Name: selenium-account
Version: 0.2.3
Summary: selenium_account
Home-page: https://github.com/kkristof200/selenium_account
Author: Kristof
Classifier: Programming Language :: Python :: 3
Classifier: License :: OSI Approved :: MIT License
Classifier: Operating System :: OS Independent
Requires-Python: >=3.5
License-File: LICENSE
